ark/__init__.py
ark/cli/__init__.py
ark/cli/cli.py
ark/cli/serve_template/Dockerfile
ark/cli/serve_template/__init__.py
ark/cli/serve_template/code/__init__.py
ark/cli/serve_template/code/main.py
ark/cli/serve_template/run.sh
ark/cli/utils/__init__.py
ark/cli/utils/cr.py
ark/cli/utils/tos.py
ark/cli/utils/vefaas.py
ark/component/__init__.py
ark/component/action/__init__.py
ark/component/action/action_call.py
ark/component/action/function_call.py
ark/component/action/search.py
ark/component/action/utils.py
ark/component/generator/__init__.py
ark/component/generator/keywords_generator.py
ark/component/generator/rag_augment_generator.py
ark/component/generator/rag_rewrite_generator.py
ark/component/llm/__init__.py
ark/component/llm/base.py
ark/component/llm/llm.py
ark/component/llm/rag_intention/__init__.py
ark/component/llm/rag_intention/rag_intention.py
ark/component/llm/rag_summary/__init__.py
ark/component/llm/rag_summary/rag_summary.py
ark/component/llm/utils.py
ark/component/output_parser/__init__.py
ark/component/output_parser/browsing_output.py
ark/component/output_parser/rag_output.py
ark/component/output_parser/reference.py
ark/component/plugins/__init__.py
ark/component/plugins/plugin.py
ark/component/plugins/search_intention.py
ark/component/plugins/search_summary.py
ark/component/prompts/__init__.py
ark/component/prompts/browsing_prompt.py
ark/component/prompts/custom_prompt.py
ark/component/prompts/group_chat_prompt.py
ark/component/prompts/rag_prompt.py
ark/component/ranker/__init__.py
ark/component/ranker/ranker.py
ark/component/reader/__init__.py
ark/component/reader/_reader.py
ark/component/reader/base_reader.py
ark/component/reader/common_reader.py
ark/component/reader/feishu_reader.py
ark/component/reader/struct_reader.py
ark/component/retriever/__init__.py
ark/component/retriever/base_retriever.py
ark/component/retriever/config.py
ark/component/retriever/vikingdb_knowledge_retriever.py
ark/component/retriever/vikingdb_retriever.py
ai_app_lab-0.1.0.dist-info/METADATA
ai_app_lab-0.1.0.dist-info/WHEEL
ai_app_lab-0.1.0.dist-info/entry_points.txt
ai_app_lab-0.1.0.dist-info/RECORD
