Metadata-Version: 2.1
Name: ai-app-lab
Version: 0.1.0
Summary: 
Author: wangsen.0914
Author-email: wangsen.0914@bytedance.com
Requires-Python: >=3.8.1,<3.12.0
Classifier: Programming Language :: Python :: 3
Classifier: Programming Language :: Python :: 3.9
Classifier: Programming Language :: Python :: 3.10
Classifier: Programming Language :: Python :: 3.11
Provides-Extra: cli
Provides-Extra: flask
Provides-Extra: ray
Requires-Dist: aiofiles (==23.2.1)
Requires-Dist: docker (>=7.0.0,<8.0.0) ; extra == "cli"
Requires-Dist: fastapi (>=0.100.0,<1.0.0)
Requires-Dist: httpx (>=0.27.0)
Requires-Dist: jinja2 (>=3.1.2,<4.0.0)
Requires-Dist: langchain (>=0.1.0,<=0.2.0)
Requires-Dist: langchain_core (==0.1.52)
Requires-Dist: opentelemetry-api (>=1.22.0,<2.0.0)
Requires-Dist: opentelemetry-exporter-otlp (>=1.22.0,<2.0.0)
Requires-Dist: opentelemetry-sdk (>=1.22.0,<2.0.0)
Requires-Dist: orjson (<3.10.7)
Requires-Dist: pandas (>=1.3.5,<3.0.0)
Requires-Dist: pydantic (>=2.0.0,<3.0.0)
Requires-Dist: pypdf (>=4.0.0,<5.0.0)
Requires-Dist: python-docx (>=1.1.0,<2.0.0)
Requires-Dist: pytz (==2020.5)
Requires-Dist: ray (>=2.9.0,<3.0.0) ; extra == "ray"
Requires-Dist: structlog (>=23.1.0,<25.0.0)
Requires-Dist: tenacity (==8.3.0)
Requires-Dist: tos (==2.6.8)
Requires-Dist: typer (>=0.9.0,<0.10.0) ; extra == "cli"
Requires-Dist: uvicorn (>=0.22.0,<0.30.0)
Requires-Dist: uvloop (>=0.19.0)
Requires-Dist: volcengine (>=1.0.146)
Requires-Dist: volcengine-python-sdk (>=1.0.95)
